{"data":{"markdownRemark":{"htmlAst":{"type":"root","children":[{"type":"text","value":"\n\n\n\n\n\n\n\n\n\n\n\n\n\n\n\n\n\n\n\n\n\n\n\n\n\n\n\n\n\n\n\n\n\n\n\n\n\n\n\n\n\n\n\n\n\n\n\n\n\n\n\n\n\n\n\n\n\n\n\n\n\n\n\n\n\n\n\n\n\n\n\n\n\n\n\n\n\n\n\n\n\n\n\n\n\n\n\n\n\n\n\n\n\n\n\n\n\n\n\n\n\n\n\n\n\n\n\n\n\n\n\n\n\n\n\n\n\n\n\n\n\n\n\n\n\n\n\n\n\n\n\n\n\n\n\n\n\n\n\n\n\n\n\n\n\n\n\n\n\n\n\n\n\n\n\n\n\n\n\n\n\n\n\n\n\n\n\n\n\n\n\n\n\n\n\n\n\n\n\n\n\n\n\n\n\n\n\n\n\n\n\n\n\n\n\n\n\n\n\n\n\n\n\n\n\n\n\n\n\n\n\n\n\n\n\n\n\n\n\n\n\n\n\n\n\n\n\n\n\n\n\n\n\n\n\n\n\n\n\n\n\n\n\n\n\n\n\n\n\n\n\n\n\n\n\n\n\n\n\n\n\n\n\n\n\n\n\n\n\n\n\n\n\n\n\n\n\n\n\n\n\n\n\n\n\n\n\n\n\n\n\n\n\n\n\n\n\n\n\n\n\n\n\n\n\n\n\n\n\n\n\n\n\n\n\n\n\n\n\n\n\n\n\n\n\n\n\n\n\n\n\n\n\n\n\n\n\n\n\n\n\n\n\n\n\n\n\n\n\n\n\n\n\n\n\n\n\n\n\n\n\n\n\n\n\n\n\n\n\n\n\n\n\n\n\n\n\n\n\n\n\n\n\n\n\n\n\n\n\n\n\n\n\n\n\n\n\n\n\n\n\n\n\n\n\n\n\n\n\n\n\n\n\n\n\n\n\n\n\n\n\n\n\n\n\n\n\n\n\n\n\n\n\n\n\n\n\n\n\n\n\n\n\n\n\n\n\n\n\n\n\n\n\n\n\n\n\n\n\n\n\n\n\n\n\n\n\n\n\n\n\n\n\n\n\n\n\n\n\n\n\n\n\n\n\n\n\n\n\n\n\n\n\n\n\n\n\n\n\n\n\n\n\n\n\n\n\n\n\n\n\n\n\n\n\n\n\n\n\n\n\n\n\n\n\n\n\n\n\n\n\n\n\n\n\n\n\n\n\n\n\n\n\n\n\n\n\n\n\n\n\n\n\n\n\n\n\n\n\n\n\n\n\n\n\n\n\n\n\n\n\n\n\n\n\n\n\n\n\n\n\n\n\n\n\n\n\n\n\n\n\n\n\n\n\n\n\n\n\n\n\n\n\n\n\n\n\n\n\n\n\n\n\n\n\n\n\n\n\n\n\n\n\n\n\n\n\n\n\n\n\n\n\n\n\n\n\n\n\n\n\n\n\n\n\n\n\n\n\n\n\n\n\n\n\n\n\n\n\n\n\n\n\n\n\n\n\n\n\n\n\n\n\n\n\n\n\n\n\n\n\n\n\n\n\n\n\n\n\n\n\n\n\n\n\n\n\n\n\n\n\n\n\n\n\n\n\n\n\n\n\n"},{"type":"element","tagName":"table","properties":{},"children":[{"type":"element","tagName":"thead","properties":{},"children":[{"type":"element","tagName":"tr","properties":{},"children":[{"type":"element","tagName":"th","properties":{},"children":[{"type":"text","value":"d100"}]},{"type":"element","tagName":"th","properties":{},"children":[{"type":"text","value":"Failed career"}]},{"type":"element","tagName":"th","properties":{},"children":[{"type":"text","value":"Item 1"}]},{"type":"element","tagName":"th","properties":{},"children":[{"type":"text","value":"Item 2"}]},{"type":"element","tagName":"th","properties":{},"children":[{"type":"text","value":"Weapon"}]}]}]},{"type":"element","tagName":"tbody","properties":{},"children":[{"type":"element","tagName":"tr","properties":{},"children":[{"type":"element","tagName":"td","properties":{},"children":[{"type":"text","value":"1"}]},{"type":"element","tagName":"td","properties":{},"children":[{"type":"text","value":"Afterlife Messenger"}]},{"type":"element","tagName":"td","properties":{},"children":[{"type":"text","value":"Rope (50ft)"}]},{"type":"element","tagName":"td","properties":{},"children":[{"type":"text","value":"Smelling salts"}]},{"type":"element","tagName":"td","properties":{},"children":[{"type":"text","value":"Scalpel (light)"}]}]},{"type":"element","tagName":"tr","properties":{},"children":[{"type":"element","tagName":"td","properties":{},"children":[{"type":"text","value":"2"}]},{"type":"element","tagName":"td","properties":{},"children":[{"type":"text","value":"Alehouse Keeper"}]},{"type":"element","tagName":"td","properties":{},"children":[{"type":"text","value":"Small barrel of ale"}]},{"type":"element","tagName":"td","properties":{},"children":[{"type":"text","value":"Tongs"}]},{"type":"element","tagName":"td","properties":{},"children":[{"type":"text","value":"Blunderbuss"}]}]},{"type":"element","tagName":"tr","properties":{},"children":[{"type":"element","tagName":"td","properties":{},"children":[{"type":"text","value":"3"}]},{"type":"element","tagName":"td","properties":{},"children":[{"type":"text","value":"Amateur Actor"}]},{"type":"element","tagName":"td","properties":{},"children":[{"type":"text","value":"Garish painted mask"}]},{"type":"element","tagName":"td","properties":{},"children":[{"type":"text","value":"Fancy clothes"}]},{"type":"element","tagName":"td","properties":{},"children":[{"type":"text","value":"Wooden sword (light)"}]}]},{"type":"element","tagName":"tr","properties":{},"children":[{"type":"element","tagName":"td","properties":{},"children":[{"type":"text","value":"4"}]},{"type":"element","tagName":"td","properties":{},"children":[{"type":"text","value":"Apothecary"}]},{"type":"element","tagName":"td","properties":{},"children":[{"type":"text","value":"Pungent herbs"}]},{"type":"element","tagName":"td","properties":{},"children":[{"type":"text","value":"Poison herbs"}]},{"type":"element","tagName":"td","properties":{},"children":[{"type":"text","value":"Dagger (light)"}]}]},{"type":"element","tagName":"tr","properties":{},"children":[{"type":"element","tagName":"td","properties":{},"children":[{"type":"text","value":"5"}]},{"type":"element","tagName":"td","properties":{},"children":[{"type":"text","value":"Arsonist-for-hire"}]},{"type":"element","tagName":"td","properties":{},"children":[{"type":"text","value":"Flask of oil"}]},{"type":"element","tagName":"td","properties":{},"children":[{"type":"text","value":"Flare"}]},{"type":"element","tagName":"td","properties":{},"children":[{"type":"text","value":"Molotov cocktail (2d6 fire to 10' radius)"}]}]},{"type":"element","tagName":"tr","properties":{},"children":[{"type":"element","tagName":"td","properties":{},"children":[{"type":"text","value":"6"}]},{"type":"element","tagName":"td","properties":{},"children":[{"type":"text","value":"Aspiring Widow"}]},{"type":"element","tagName":"td","properties":{},"children":[{"type":"text","value":"Vial of poison"}]},{"type":"element","tagName":"td","properties":{},"children":[{"type":"text","value":"Fake gold ring"}]},{"type":"element","tagName":"td","properties":{},"children":[{"type":"text","value":"Dagger (light)"}]}]},{"type":"element","tagName":"tr","properties":{},"children":[{"type":"element","tagName":"td","properties":{},"children":[{"type":"text","value":"7"}]},{"type":"element","tagName":"td","properties":{},"children":[{"type":"text","value":"Banned Guild Explorer"}]},{"type":"element","tagName":"td","properties":{},"children":[{"type":"text","value":"Pot of tar"}]},{"type":"element","tagName":"td","properties":{},"children":[{"type":"text","value":"Treasure map (DM rolls secretly: 1-3 accurate; 4-5 wrong; 6 dangerous)"}]},{"type":"element","tagName":"td","properties":{},"children":[{"type":"text","value":"Rifle"}]}]},{"type":"element","tagName":"tr","properties":{},"children":[{"type":"element","tagName":"td","properties":{},"children":[{"type":"text","value":"8"}]},{"type":"element","tagName":"td","properties":{},"children":[{"type":"text","value":"Barber-surgeon"}]},{"type":"element","tagName":"td","properties":{},"children":[{"type":"text","value":"Soap"}]},{"type":"element","tagName":"td","properties":{},"children":[{"type":"text","value":"Flask of oil"}]},{"type":"element","tagName":"td","properties":{},"children":[{"type":"text","value":"Scalpel (light)"}]}]},{"type":"element","tagName":"tr","properties":{},"children":[{"type":"element","tagName":"td","properties":{},"children":[{"type":"text","value":"9"}]},{"type":"element","tagName":"td","properties":{},"children":[{"type":"text","value":"Barnacle Scraper"}]},{"type":"element","tagName":"td","properties":{},"children":[{"type":"text","value":"Sack"}]},{"type":"element","tagName":"td","properties":{},"children":[{"type":"text","value":"Chisel"}]},{"type":"element","tagName":"td","properties":{},"children":[{"type":"text","value":"Scraping knife (light)"}]}]},{"type":"element","tagName":"tr","properties":{},"children":[{"type":"element","tagName":"td","properties":{},"children":[{"type":"text","value":"10"}]},{"type":"element","tagName":"td","properties":{},"children":[{"type":"text","value":"Bathhouse Scrubber"}]},{"type":"element","tagName":"td","properties":{},"children":[{"type":"text","value":"Soap"}]},{"type":"element","tagName":"td","properties":{},"children":[{"type":"text","value":"Large sponge"}]},{"type":"element","tagName":"td","properties":{},"children":[{"type":"text","value":"Heavy scrubbing brush (light)"}]}]},{"type":"element","tagName":"tr","properties":{},"children":[{"type":"element","tagName":"td","properties":{},"children":[{"type":"text","value":"11"}]},{"type":"element","tagName":"td","properties":{},"children":[{"type":"text","value":"Bell Ringer"}]},{"type":"element","tagName":"td","properties":{},"children":[{"type":"text","value":"Iron hand bell"}]},{"type":"element","tagName":"td","properties":{},"children":[{"type":"text","value":"Pocketwatch (broken)"}]},{"type":"element","tagName":"td","properties":{},"children":[{"type":"text","value":"Wooden club (light)"}]}]},{"type":"element","tagName":"tr","properties":{},"children":[{"type":"element","tagName":"td","properties":{},"children":[{"type":"text","value":"12"}]},{"type":"element","tagName":"td","properties":{},"children":[{"type":"text","value":"Big Game Huntee"}]},{"type":"element","tagName":"td","properties":{},"children":[{"type":"text","value":"Brightly-patterned tunic"}]},{"type":"element","tagName":"td","properties":{},"children":[{"type":"text","value":"Bag of caltrops"}]},{"type":"element","tagName":"td","properties":{},"children":[{"type":"text","value":"Spear (medium)"}]}]},{"type":"element","tagName":"tr","properties":{},"children":[{"type":"element","tagName":"td","properties":{},"children":[{"type":"text","value":"13"}]},{"type":"element","tagName":"td","properties":{},"children":[{"type":"text","value":"Bill Paster"}]},{"type":"element","tagName":"td","properties":{},"children":[{"type":"text","value":"Flask of glue"}]},{"type":"element","tagName":"td","properties":{},"children":[{"type":"text","value":"Large brush"}]},{"type":"element","tagName":"td","properties":{},"children":[{"type":"text","value":"Flail (medium)"}]}]},{"type":"element","tagName":"tr","properties":{},"children":[{"type":"element","tagName":"td","properties":{},"children":[{"type":"text","value":"14"}]},{"type":"element","tagName":"td","properties":{},"children":[{"type":"text","value":"Blood Donor"}]},{"type":"element","tagName":"td","properties":{},"children":[{"type":"text","value":"Jar of blood"}]},{"type":"element","tagName":"td","properties":{},"children":[{"type":"text","value":"Bandages"}]},{"type":"element","tagName":"td","properties":{},"children":[{"type":"text","value":"Dagger (light)"}]}]},{"type":"element","tagName":"tr","properties":{},"children":[{"type":"element","tagName":"td","properties":{},"children":[{"type":"text","value":"15"}]},{"type":"element","tagName":"td","properties":{},"children":[{"type":"text","value":"Body Double"}]},{"type":"element","tagName":"td","properties":{},"children":[{"type":"text","value":"Disguise kit"}]},{"type":"element","tagName":"td","properties":{},"children":[{"type":"text","value":"Fancy clothes"}]},{"type":"element","tagName":"td","properties":{},"children":[{"type":"text","value":"Rapier (medium)"}]}]},{"type":"element","tagName":"tr","properties":{},"children":[{"type":"element","tagName":"td","properties":{},"children":[{"type":"text","value":"16"}]},{"type":"element","tagName":"td","properties":{},"children":[{"type":"text","value":"Boilermaker's Apprentice"}]},{"type":"element","tagName":"td","properties":{},"children":[{"type":"text","value":"Grease"}]},{"type":"element","tagName":"td","properties":{},"children":[{"type":"text","value":"Iron spikes"}]},{"type":"element","tagName":"td","properties":{},"children":[{"type":"text","value":"Sledgehammer (medium)"}]}]},{"type":"element","tagName":"tr","properties":{},"children":[{"type":"element","tagName":"td","properties":{},"children":[{"type":"text","value":"17"}]},{"type":"element","tagName":"td","properties":{},"children":[{"type":"text","value":"Bone Collector"}]},{"type":"element","tagName":"td","properties":{},"children":[{"type":"text","value":"Crowbar"}]},{"type":"element","tagName":"td","properties":{},"children":[{"type":"text","value":"Candles"}]},{"type":"element","tagName":"td","properties":{},"children":[{"type":"text","value":"Sledgehammer (medium)"}]}]},{"type":"element","tagName":"tr","properties":{},"children":[{"type":"element","tagName":"td","properties":{},"children":[{"type":"text","value":"18"}]},{"type":"element","tagName":"td","properties":{},"children":[{"type":"text","value":"Bounty Hunter"}]},{"type":"element","tagName":"td","properties":{},"children":[{"type":"text","value":"Net"}]},{"type":"element","tagName":"td","properties":{},"children":[{"type":"text","value":"Rope (50ft)"}]},{"type":"element","tagName":"td","properties":{},"children":[{"type":"text","value":"Crossbow"}]}]},{"type":"element","tagName":"tr","properties":{},"children":[{"type":"element","tagName":"td","properties":{},"children":[{"type":"text","value":"19"}]},{"type":"element","tagName":"td","properties":{},"children":[{"type":"text","value":"Breechesmaker"}]},{"type":"element","tagName":"td","properties":{},"children":[{"type":"text","value":"Waterproof trousers"}]},{"type":"element","tagName":"td","properties":{},"children":[{"type":"text","value":"Tin of leather oil"}]},{"type":"element","tagName":"td","properties":{},"children":[{"type":"text","value":"Clippers (light)"}]}]},{"type":"element","tagName":"tr","properties":{},"children":[{"type":"element","tagName":"td","properties":{},"children":[{"type":"text","value":"20"}]},{"type":"element","tagName":"td","properties":{},"children":[{"type":"text","value":"Bridge Warden"}]},{"type":"element","tagName":"td","properties":{},"children":[{"type":"text","value":"Hand bell"}]},{"type":"element","tagName":"td","properties":{},"children":[{"type":"text","value":"Chain (10ft)"}]},{"type":"element","tagName":"td","properties":{},"children":[{"type":"text","value":"Rifle"}]}]},{"type":"element","tagName":"tr","properties":{},"children":[{"type":"element","tagName":"td","properties":{},"children":[{"type":"text","value":"21"}]},{"type":"element","tagName":"td","properties":{},"children":[{"type":"text","value":"Cat Court Clerk"}]},{"type":"element","tagName":"td","properties":{},"children":[{"type":"text","value":"Grey curly wig"}]},{"type":"element","tagName":"td","properties":{},"children":[{"type":"text","value":"Small silver bell"}]},{"type":"element","tagName":"td","properties":{},"children":[{"type":"text","value":"Pistol"}]}]},{"type":"element","tagName":"tr","properties":{},"children":[{"type":"element","tagName":"td","properties":{},"children":[{"type":"text","value":"22"}]},{"type":"element","tagName":"td","properties":{},"children":[{"type":"text","value":"Caveborn Child"}]},{"type":"element","tagName":"td","properties":{},"children":[{"type":"text","value":"Wolf-skin cloak"}]},{"type":"element","tagName":"td","properties":{},"children":[{"type":"text","value":"\"Special: See in dim light, blind in bright light\""}]},{"type":"element","tagName":"td","properties":{},"children":[{"type":"text","value":"Stone axe (medium)"}]}]},{"type":"element","tagName":"tr","properties":{},"children":[{"type":"element","tagName":"td","properties":{},"children":[{"type":"text","value":"23"}]},{"type":"element","tagName":"td","properties":{},"children":[{"type":"text","value":"Certified Executioner"}]},{"type":"element","tagName":"td","properties":{},"children":[{"type":"text","value":"Basket"}]},{"type":"element","tagName":"td","properties":{},"children":[{"type":"text","value":"Shovel"}]},{"type":"element","tagName":"td","properties":{},"children":[{"type":"text","value":"Battle axe (heavy)"}]}]},{"type":"element","tagName":"tr","properties":{},"children":[{"type":"element","tagName":"td","properties":{},"children":[{"type":"text","value":"24"}]},{"type":"element","tagName":"td","properties":{},"children":[{"type":"text","value":"Checkers Hustler"}]},{"type":"element","tagName":"td","properties":{},"children":[{"type":"text","value":"Checkers set"}]},{"type":"element","tagName":"td","properties":{},"children":[{"type":"text","value":"Fake gold coins"}]},{"type":"element","tagName":"td","properties":{},"children":[{"type":"text","value":"Dagger (light)"}]}]},{"type":"element","tagName":"tr","properties":{},"children":[{"type":"element","tagName":"td","properties":{},"children":[{"type":"text","value":"25"}]},{"type":"element","tagName":"td","properties":{},"children":[{"type":"text","value":"Cheesemaker"}]},{"type":"element","tagName":"td","properties":{},"children":[{"type":"text","value":"Wheel of pungent cheese"}]},{"type":"element","tagName":"td","properties":{},"children":[{"type":"text","value":"Cheesecloth"}]},{"type":"element","tagName":"td","properties":{},"children":[{"type":"text","value":"Knife (light)"}]}]},{"type":"element","tagName":"tr","properties":{},"children":[{"type":"element","tagName":"td","properties":{},"children":[{"type":"text","value":"26"}]},{"type":"element","tagName":"td","properties":{},"children":[{"type":"text","value":"Corpse Digger"}]},{"type":"element","tagName":"td","properties":{},"children":[{"type":"text","value":"Shovel"}]},{"type":"element","tagName":"td","properties":{},"children":[{"type":"text","value":"Crowbar"}]},{"type":"element","tagName":"td","properties":{},"children":[{"type":"text","value":"Pickaxe (medium)"}]}]},{"type":"element","tagName":"tr","properties":{},"children":[{"type":"element","tagName":"td","properties":{},"children":[{"type":"text","value":"27"}]},{"type":"element","tagName":"td","properties":{},"children":[{"type":"text","value":"Crab Wrangler"}]},{"type":"element","tagName":"td","properties":{},"children":[{"type":"text","value":"Net"}]},{"type":"element","tagName":"td","properties":{},"children":[{"type":"text","value":"Tame landcrab"}]},{"type":"element","tagName":"td","properties":{},"children":[{"type":"text","value":"Spear (medium)"}]}]},{"type":"element","tagName":"tr","properties":{},"children":[{"type":"element","tagName":"td","properties":{},"children":[{"type":"text","value":"28"}]},{"type":"element","tagName":"td","properties":{},"children":[{"type":"text","value":"Defrosted Ancient"}]},{"type":"element","tagName":"td","properties":{},"children":[{"type":"text","value":"Random Device"}]},{"type":"element","tagName":"td","properties":{},"children":[{"type":"text","value":"Special: 2-in-6 chance to identify Devices"}]},{"type":"element","tagName":"td","properties":{},"children":[{"type":"text","value":"Iron bar (light)"}]}]},{"type":"element","tagName":"tr","properties":{},"children":[{"type":"element","tagName":"td","properties":{},"children":[{"type":"text","value":"29"}]},{"type":"element","tagName":"td","properties":{},"children":[{"type":"text","value":"Demon House Gardener"}]},{"type":"element","tagName":"td","properties":{},"children":[{"type":"text","value":"Demon house livery"}]},{"type":"element","tagName":"td","properties":{},"children":[{"type":"text","value":"Rake"}]},{"type":"element","tagName":"td","properties":{},"children":[{"type":"text","value":"Hedge shears (medium)"}]}]},{"type":"element","tagName":"tr","properties":{},"children":[{"type":"element","tagName":"td","properties":{},"children":[{"type":"text","value":"30"}]},{"type":"element","tagName":"td","properties":{},"children":[{"type":"text","value":"Demon House Servant"}]},{"type":"element","tagName":"td","properties":{},"children":[{"type":"text","value":"Demon house livery"}]},{"type":"element","tagName":"td","properties":{},"children":[{"type":"text","value":"Candles"}]},{"type":"element","tagName":"td","properties":{},"children":[{"type":"text","value":"Dagger (light)"}]}]},{"type":"element","tagName":"tr","properties":{},"children":[{"type":"element","tagName":"td","properties":{},"children":[{"type":"text","value":"31"}]},{"type":"element","tagName":"td","properties":{},"children":[{"type":"text","value":"Deserting Conscript"}]},{"type":"element","tagName":"td","properties":{},"children":[{"type":"text","value":"Soldier's uniform"}]},{"type":"element","tagName":"td","properties":{},"children":[{"type":"text","value":"Pair of dice"}]},{"type":"element","tagName":"td","properties":{},"children":[{"type":"text","value":"Rifle"}]}]},{"type":"element","tagName":"tr","properties":{},"children":[{"type":"element","tagName":"td","properties":{},"children":[{"type":"text","value":"32"}]},{"type":"element","tagName":"td","properties":{},"children":[{"type":"text","value":"Dish Pig"}]},{"type":"element","tagName":"td","properties":{},"children":[{"type":"text","value":"Roll of clean teatowels"}]},{"type":"element","tagName":"td","properties":{},"children":[{"type":"text","value":"Cookpot"}]},{"type":"element","tagName":"td","properties":{},"children":[{"type":"text","value":"Spiked club (light)"}]}]},{"type":"element","tagName":"tr","properties":{},"children":[{"type":"element","tagName":"td","properties":{},"children":[{"type":"text","value":"33"}]},{"type":"element","tagName":"td","properties":{},"children":[{"type":"text","value":"Dodgy Pardoner"}]},{"type":"element","tagName":"td","properties":{},"children":[{"type":"text","value":"Bones of a saint (probably)"}]},{"type":"element","tagName":"td","properties":{},"children":[{"type":"text","value":"Lens"}]},{"type":"element","tagName":"td","properties":{},"children":[{"type":"text","value":"Sickle (light)"}]}]},{"type":"element","tagName":"tr","properties":{},"children":[{"type":"element","tagName":"td","properties":{},"children":[{"type":"text","value":"34"}]},{"type":"element","tagName":"td","properties":{},"children":[{"type":"text","value":"Dreamsmoke Sot"}]},{"type":"element","tagName":"td","properties":{},"children":[{"type":"text","value":"Pipe"}]},{"type":"element","tagName":"td","properties":{},"children":[{"type":"text","value":"Wad of condensed dreamstuff"}]},{"type":"element","tagName":"td","properties":{},"children":[{"type":"text","value":"Dagger (light)"}]}]},{"type":"element","tagName":"tr","properties":{},"children":[{"type":"element","tagName":"td","properties":{},"children":[{"type":"text","value":"35"}]},{"type":"element","tagName":"td","properties":{},"children":[{"type":"text","value":"Egg Dealer"}]},{"type":"element","tagName":"td","properties":{},"children":[{"type":"text","value":"Eggs (12)"}]},{"type":"element","tagName":"td","properties":{},"children":[{"type":"text","value":"Basket"}]},{"type":"element","tagName":"td","properties":{},"children":[{"type":"text","value":"Staff (light)"}]}]},{"type":"element","tagName":"tr","properties":{},"children":[{"type":"element","tagName":"td","properties":{},"children":[{"type":"text","value":"36"}]},{"type":"element","tagName":"td","properties":{},"children":[{"type":"text","value":"Engine Stoker"}]},{"type":"element","tagName":"td","properties":{},"children":[{"type":"text","value":"Shovel"}]},{"type":"element","tagName":"td","properties":{},"children":[{"type":"text","value":"Small sack of coal"}]},{"type":"element","tagName":"td","properties":{},"children":[{"type":"text","value":"Iron bar (light)"}]}]},{"type":"element","tagName":"tr","properties":{},"children":[{"type":"element","tagName":"td","properties":{},"children":[{"type":"text","value":"37"}]},{"type":"element","tagName":"td","properties":{},"children":[{"type":"text","value":"Escaped Dream-slave"}]},{"type":"element","tagName":"td","properties":{},"children":[{"type":"text","value":"Jar of dreams"}]},{"type":"element","tagName":"td","properties":{},"children":[{"type":"text","value":"Manacles"}]},{"type":"element","tagName":"td","properties":{},"children":[{"type":"text","value":"Dagger (light)"}]}]},{"type":"element","tagName":"tr","properties":{},"children":[{"type":"element","tagName":"td","properties":{},"children":[{"type":"text","value":"38"}]},{"type":"element","tagName":"td","properties":{},"children":[{"type":"text","value":"Fall Guy"}]},{"type":"element","tagName":"td","properties":{},"children":[{"type":"text","value":"Disguse kit"}]},{"type":"element","tagName":"td","properties":{},"children":[{"type":"text","value":"Rope (50ft)"}]},{"type":"element","tagName":"td","properties":{},"children":[{"type":"text","value":"Sword (medium)"}]}]},{"type":"element","tagName":"tr","properties":{},"children":[{"type":"element","tagName":"td","properties":{},"children":[{"type":"text","value":"39"}]},{"type":"element","tagName":"td","properties":{},"children":[{"type":"text","value":"Fallen Sky-pirate"}]},{"type":"element","tagName":"td","properties":{},"children":[{"type":"text","value":"Grappling hook"}]},{"type":"element","tagName":"td","properties":{},"children":[{"type":"text","value":"Rope (50ft)"}]},{"type":"element","tagName":"td","properties":{},"children":[{"type":"text","value":"\"Harpoon gun (d10 damage, 3 slots, 2 hands, 1 round to reload)\""}]}]},{"type":"element","tagName":"tr","properties":{},"children":[{"type":"element","tagName":"td","properties":{},"children":[{"type":"text","value":"40"}]},{"type":"element","tagName":"td","properties":{},"children":[{"type":"text","value":"False Prophet"}]},{"type":"element","tagName":"td","properties":{},"children":[{"type":"text","value":"Holy symbol"}]},{"type":"element","tagName":"td","properties":{},"children":[{"type":"text","value":"Devoted follower"}]},{"type":"element","tagName":"td","properties":{},"children":[{"type":"text","value":"Staff (light)"}]}]},{"type":"element","tagName":"tr","properties":{},"children":[{"type":"element","tagName":"td","properties":{},"children":[{"type":"text","value":"41"}]},{"type":"element","tagName":"td","properties":{},"children":[{"type":"text","value":"Forgotten Prisoner"}]},{"type":"element","tagName":"td","properties":{},"children":[{"type":"text","value":"Chain (10ft)"}]},{"type":"element","tagName":"td","properties":{},"children":[{"type":"text","value":"Manacles"}]},{"type":"element","tagName":"td","properties":{},"children":[{"type":"text","value":"Iron bar (light)"}]}]},{"type":"element","tagName":"tr","properties":{},"children":[{"type":"element","tagName":"td","properties":{},"children":[{"type":"text","value":"42"}]},{"type":"element","tagName":"td","properties":{},"children":[{"type":"text","value":"Fraudulent Stockbroker"}]},{"type":"element","tagName":"td","properties":{},"children":[{"type":"text","value":"Flask of oil"}]},{"type":"element","tagName":"td","properties":{},"children":[{"type":"text","value":"6 stock certificates (worthless)"}]},{"type":"element","tagName":"td","properties":{},"children":[]}]},{"type":"element","tagName":"tr","properties":{},"children":[{"type":"element","tagName":"td","properties":{},"children":[{"type":"text","value":"43"}]},{"type":"element","tagName":"td","properties":{},"children":[{"type":"text","value":"Fungus Farmer"}]},{"type":"element","tagName":"td","properties":{},"children":[{"type":"text","value":"Dried exotic mushrooms"}]},{"type":"element","tagName":"td","properties":{},"children":[{"type":"text","value":"Lantern (ultraviolet)"}]},{"type":"element","tagName":"td","properties":{},"children":[{"type":"text","value":"Staff (light)"}]}]},{"type":"element","tagName":"tr","properties":{},"children":[{"type":"element","tagName":"td","properties":{},"children":[{"type":"text","value":"44"}]},{"type":"element","tagName":"td","properties":{},"children":[{"type":"text","value":"Ghost Vessal"}]},{"type":"element","tagName":"td","properties":{},"children":[{"type":"text","value":"Angry ghost (trapped in jar)"}]},{"type":"element","tagName":"td","properties":{},"children":[{"type":"text","value":"Candles"}]},{"type":"element","tagName":"td","properties":{},"children":[{"type":"text","value":"Sword (medium)"}]}]},{"type":"element","tagName":"tr","properties":{},"children":[{"type":"element","tagName":"td","properties":{},"children":[{"type":"text","value":"45"}]},{"type":"element","tagName":"td","properties":{},"children":[{"type":"text","value":"Goblin Aristocrat"}]},{"type":"element","tagName":"td","properties":{},"children":[{"type":"text","value":"Shield bearing family crest"}]},{"type":"element","tagName":"td","properties":{},"children":[{"type":"text","value":"\"Deed to a crumbling mansion, somewhere in the Sunken-lands\""}]},{"type":"element","tagName":"td","properties":{},"children":[{"type":"text","value":"Sword (medium)"}]}]},{"type":"element","tagName":"tr","properties":{},"children":[{"type":"element","tagName":"td","properties":{},"children":[{"type":"text","value":"46"}]},{"type":"element","tagName":"td","properties":{},"children":[{"type":"text","value":"Good Dog"}]},{"type":"element","tagName":"td","properties":{},"children":[{"type":"text","value":"Collar"}]},{"type":"element","tagName":"td","properties":{},"children":[{"type":"text","value":"Special: You are a dog"}]},{"type":"element","tagName":"td","properties":{},"children":[{"type":"text","value":"Teeth (medium)"}]}]},{"type":"element","tagName":"tr","properties":{},"children":[{"type":"element","tagName":"td","properties":{},"children":[{"type":"text","value":"47"}]},{"type":"element","tagName":"td","properties":{},"children":[{"type":"text","value":"Gutter Wretch"}]},{"type":"element","tagName":"td","properties":{},"children":[{"type":"text","value":"Bucket"}]},{"type":"element","tagName":"td","properties":{},"children":[{"type":"text","value":"Bundle of paper"}]},{"type":"element","tagName":"td","properties":{},"children":[]}]},{"type":"element","tagName":"tr","properties":{},"children":[{"type":"element","tagName":"td","properties":{},"children":[{"type":"text","value":"48"}]},{"type":"element","tagName":"td","properties":{},"children":[{"type":"text","value":"Half-breed Mutant"}]},{"type":"element","tagName":"td","properties":{},"children":[{"type":"text","value":"Padlock"}]},{"type":"element","tagName":"td","properties":{},"children":[{"type":"text","value":"\"Special: Half human, half... (1 dog; 2 pig; 3 rat; 4 eel; 5 frog; 6 demon) \""}]},{"type":"element","tagName":"td","properties":{},"children":[{"type":"text","value":"Mace (medium)"}]}]},{"type":"element","tagName":"tr","properties":{},"children":[{"type":"element","tagName":"td","properties":{},"children":[{"type":"text","value":"49"}]},{"type":"element","tagName":"td","properties":{},"children":[{"type":"text","value":"Hedge Knight"}]},{"type":"element","tagName":"td","properties":{},"children":[{"type":"text","value":"Bedroll"}]},{"type":"element","tagName":"td","properties":{},"children":[{"type":"text","value":"Old horse"}]},{"type":"element","tagName":"td","properties":{},"children":[{"type":"text","value":"Trusty sword (medium)"}]}]},{"type":"element","tagName":"tr","properties":{},"children":[{"type":"element","tagName":"td","properties":{},"children":[{"type":"text","value":"50"}]},{"type":"element","tagName":"td","properties":{},"children":[{"type":"text","value":"Insurance Inspector"}]},{"type":"element","tagName":"td","properties":{},"children":[{"type":"text","value":"Chalk"}]},{"type":"element","tagName":"td","properties":{},"children":[{"type":"text","value":"Pen & ink"}]},{"type":"element","tagName":"td","properties":{},"children":[{"type":"text","value":"Pistol"}]}]},{"type":"element","tagName":"tr","properties":{},"children":[{"type":"element","tagName":"td","properties":{},"children":[{"type":"text","value":"51"}]},{"type":"element","tagName":"td","properties":{},"children":[{"type":"text","value":"Junkyard Picker"}]},{"type":"element","tagName":"td","properties":{},"children":[{"type":"text","value":"Broken pocketwatch"}]},{"type":"element","tagName":"td","properties":{},"children":[{"type":"text","value":"Pole (10ft)"}]},{"type":"element","tagName":"td","properties":{},"children":[{"type":"text","value":"Rusty axe (medium)"}]}]},{"type":"element","tagName":"tr","properties":{},"children":[{"type":"element","tagName":"td","properties":{},"children":[{"type":"text","value":"52"}]},{"type":"element","tagName":"td","properties":{},"children":[{"type":"text","value":"Kitchen Rat"}]},{"type":"element","tagName":"td","properties":{},"children":[{"type":"text","value":"Large cured sausage"}]},{"type":"element","tagName":"td","properties":{},"children":[{"type":"text","value":"Cookpot"}]},{"type":"element","tagName":"td","properties":{},"children":[{"type":"text","value":"Cleaver (light)"}]}]},{"type":"element","tagName":"tr","properties":{},"children":[{"type":"element","tagName":"td","properties":{},"children":[{"type":"text","value":"53"}]},{"type":"element","tagName":"td","properties":{},"children":[{"type":"text","value":"Lamplighter"}]},{"type":"element","tagName":"td","properties":{},"children":[{"type":"text","value":"Pole (10ft)"}]},{"type":"element","tagName":"td","properties":{},"children":[{"type":"text","value":"Lantern"}]},{"type":"element","tagName":"td","properties":{},"children":[{"type":"text","value":"Club (light)"}]}]},{"type":"element","tagName":"tr","properties":{},"children":[{"type":"element","tagName":"td","properties":{},"children":[{"type":"text","value":"54"}]},{"type":"element","tagName":"td","properties":{},"children":[{"type":"text","value":"Landtrain Conductor"}]},{"type":"element","tagName":"td","properties":{},"children":[{"type":"text","value":"Whistle"}]},{"type":"element","tagName":"td","properties":{},"children":[{"type":"text","value":"Bellows"}]},{"type":"element","tagName":"td","properties":{},"children":[{"type":"text","value":"Cudgel (light)"}]}]},{"type":"element","tagName":"tr","properties":{},"children":[{"type":"element","tagName":"td","properties":{},"children":[{"type":"text","value":"55"}]},{"type":"element","tagName":"td","properties":{},"children":[{"type":"text","value":"Lewd Sculptor"}]},{"type":"element","tagName":"td","properties":{},"children":[{"type":"text","value":"Suggestive sculpure"}]},{"type":"element","tagName":"td","properties":{},"children":[{"type":"text","value":"Small mirror"}]},{"type":"element","tagName":"td","properties":{},"children":[{"type":"text","value":"Chisel (light)"}]}]},{"type":"element","tagName":"tr","properties":{},"children":[{"type":"element","tagName":"td","properties":{},"children":[{"type":"text","value":"56"}]},{"type":"element","tagName":"td","properties":{},"children":[{"type":"text","value":"Lore Hoarder"}]},{"type":"element","tagName":"td","properties":{},"children":[{"type":"text","value":"Padlocked book"}]},{"type":"element","tagName":"td","properties":{},"children":[{"type":"text","value":"Hourglass"}]},{"type":"element","tagName":"td","properties":{},"children":[{"type":"text","value":"Staff (light)"}]}]},{"type":"element","tagName":"tr","properties":{},"children":[{"type":"element","tagName":"td","properties":{},"children":[{"type":"text","value":"57"}]},{"type":"element","tagName":"td","properties":{},"children":[{"type":"text","value":"Luckless Gambler"}]},{"type":"element","tagName":"td","properties":{},"children":[{"type":"text","value":"Pair of loaded dice"}]},{"type":"element","tagName":"td","properties":{},"children":[{"type":"text","value":"Deck of cards"}]},{"type":"element","tagName":"td","properties":{},"children":[{"type":"text","value":"Pistol"}]}]},{"type":"element","tagName":"tr","properties":{},"children":[{"type":"element","tagName":"td","properties":{},"children":[{"type":"text","value":"58"}]},{"type":"element","tagName":"td","properties":{},"children":[{"type":"text","value":"Machine Whisperer"}]},{"type":"element","tagName":"td","properties":{},"children":[{"type":"text","value":"Iron spikes"}]},{"type":"element","tagName":"td","properties":{},"children":[{"type":"text","value":"Flask of grease"}]},{"type":"element","tagName":"td","properties":{},"children":[{"type":"text","value":"Wrench (light)"}]}]},{"type":"element","tagName":"tr","properties":{},"children":[{"type":"element","tagName":"td","properties":{},"children":[{"type":"text","value":"59"}]},{"type":"element","tagName":"td","properties":{},"children":[{"type":"text","value":"Mangled Machinist"}]},{"type":"element","tagName":"td","properties":{},"children":[{"type":"text","value":"Bag of ball bearings"}]},{"type":"element","tagName":"td","properties":{},"children":[{"type":"text","value":"Metal file"}]},{"type":"element","tagName":"td","properties":{},"children":[{"type":"text","value":"Sledgehammer (medium)"}]}]},{"type":"element","tagName":"tr","properties":{},"children":[{"type":"element","tagName":"td","properties":{},"children":[{"type":"text","value":"60"}]},{"type":"element","tagName":"td","properties":{},"children":[{"type":"text","value":"Marshland Boatman"}]},{"type":"element","tagName":"td","properties":{},"children":[{"type":"text","value":"Net"}]},{"type":"element","tagName":"td","properties":{},"children":[{"type":"text","value":"Pole (10ft)"}]},{"type":"element","tagName":"td","properties":{},"children":[{"type":"text","value":"Oar (light)"}]}]},{"type":"element","tagName":"tr","properties":{},"children":[{"type":"element","tagName":"td","properties":{},"children":[{"type":"text","value":"61"}]},{"type":"element","tagName":"td","properties":{},"children":[{"type":"text","value":"Match Seller"}]},{"type":"element","tagName":"td","properties":{},"children":[{"type":"text","value":"Box of matches"}]},{"type":"element","tagName":"td","properties":{},"children":[{"type":"text","value":"Lantern"}]},{"type":"element","tagName":"td","properties":{},"children":[{"type":"text","value":"Dagger (light)"}]}]},{"type":"element","tagName":"tr","properties":{},"children":[{"type":"element","tagName":"td","properties":{},"children":[{"type":"text","value":"62"}]},{"type":"element","tagName":"td","properties":{},"children":[{"type":"text","value":"Mist Kingdom Exile"}]},{"type":"element","tagName":"td","properties":{},"children":[{"type":"text","value":"Bag of glass marbles"}]},{"type":"element","tagName":"td","properties":{},"children":[{"type":"text","value":"Special: Ignore first 20' of falling damage"}]},{"type":"element","tagName":"td","properties":{},"children":[{"type":"text","value":"Sword (medium)"}]}]},{"type":"element","tagName":"tr","properties":{},"children":[{"type":"element","tagName":"td","properties":{},"children":[{"type":"text","value":"63"}]},{"type":"element","tagName":"td","properties":{},"children":[{"type":"text","value":"Mourner"}]},{"type":"element","tagName":"td","properties":{},"children":[{"type":"text","value":"Bag of ash"}]},{"type":"element","tagName":"td","properties":{},"children":[{"type":"text","value":"Special: Can sense nearby undead"}]},{"type":"element","tagName":"td","properties":{},"children":[{"type":"text","value":"Cerimonial knife (light)"}]}]},{"type":"element","tagName":"tr","properties":{},"children":[{"type":"element","tagName":"td","properties":{},"children":[{"type":"text","value":"64"}]},{"type":"element","tagName":"td","properties":{},"children":[{"type":"text","value":"Mud Sifter"}]},{"type":"element","tagName":"td","properties":{},"children":[{"type":"text","value":"Waterproof trousers"}]},{"type":"element","tagName":"td","properties":{},"children":[{"type":"text","value":"Silt pan"}]},{"type":"element","tagName":"td","properties":{},"children":[]}]},{"type":"element","tagName":"tr","properties":{},"children":[{"type":"element","tagName":"td","properties":{},"children":[{"type":"text","value":"65"}]},{"type":"element","tagName":"td","properties":{},"children":[{"type":"text","value":"Oozeherd"}]},{"type":"element","tagName":"td","properties":{},"children":[{"type":"text","value":"Bucket"}]},{"type":"element","tagName":"td","properties":{},"children":[{"type":"text","value":"Tame ooze"}]},{"type":"element","tagName":"td","properties":{},"children":[{"type":"text","value":"Spear (medium)"}]}]},{"type":"element","tagName":"tr","properties":{},"children":[{"type":"element","tagName":"td","properties":{},"children":[{"type":"text","value":"66"}]},{"type":"element","tagName":"td","properties":{},"children":[{"type":"text","value":"Oyster Dredger"}]},{"type":"element","tagName":"td","properties":{},"children":[{"type":"text","value":"Net"}]},{"type":"element","tagName":"td","properties":{},"children":[{"type":"text","value":"Bag of oysters"}]},{"type":"element","tagName":"td","properties":{},"children":[{"type":"text","value":"Shucking knife (light)"}]}]},{"type":"element","tagName":"tr","properties":{},"children":[{"type":"element","tagName":"td","properties":{},"children":[{"type":"text","value":"67"}]},{"type":"element","tagName":"td","properties":{},"children":[{"type":"text","value":"Palanquin Bearer"}]},{"type":"element","tagName":"td","properties":{},"children":[{"type":"text","value":"Veil"}]},{"type":"element","tagName":"td","properties":{},"children":[{"type":"text","value":"Perfume"}]},{"type":"element","tagName":"td","properties":{},"children":[{"type":"text","value":"Hidden knife (light)"}]}]},{"type":"element","tagName":"tr","properties":{},"children":[{"type":"element","tagName":"td","properties":{},"children":[{"type":"text","value":"68"}]},{"type":"element","tagName":"td","properties":{},"children":[{"type":"text","value":"Pauper Noble"}]},{"type":"element","tagName":"td","properties":{},"children":[{"type":"text","value":"Monogrammed handkerchief"}]},{"type":"element","tagName":"td","properties":{},"children":[{"type":"text","value":"Old horse"}]},{"type":"element","tagName":"td","properties":{},"children":[{"type":"text","value":"Rapier (medium)"}]}]},{"type":"element","tagName":"tr","properties":{},"children":[{"type":"element","tagName":"td","properties":{},"children":[{"type":"text","value":"69"}]},{"type":"element","tagName":"td","properties":{},"children":[{"type":"text","value":"Poltergeist Lure"}]},{"type":"element","tagName":"td","properties":{},"children":[{"type":"text","value":"Candles"}]},{"type":"element","tagName":"td","properties":{},"children":[{"type":"text","value":"Spirit jar"}]},{"type":"element","tagName":"td","properties":{},"children":[{"type":"text","value":"\"Spectral blade (light, can attack ghosts)\""}]}]},{"type":"element","tagName":"tr","properties":{},"children":[{"type":"element","tagName":"td","properties":{},"children":[{"type":"text","value":"70"}]},{"type":"element","tagName":"td","properties":{},"children":[{"type":"text","value":"Prison Hulk Escapee"}]},{"type":"element","tagName":"td","properties":{},"children":[{"type":"text","value":"Grappling hook"}]},{"type":"element","tagName":"td","properties":{},"children":[{"type":"text","value":"Wooden spikes"}]},{"type":"element","tagName":"td","properties":{},"children":[{"type":"text","value":"Shiv (light)"}]}]},{"type":"element","tagName":"tr","properties":{},"children":[{"type":"element","tagName":"td","properties":{},"children":[{"type":"text","value":"71"}]},{"type":"element","tagName":"td","properties":{},"children":[{"type":"text","value":"Prize-losing Pugilist"}]},{"type":"element","tagName":"td","properties":{},"children":[{"type":"text","value":"Hand bell"}]},{"type":"element","tagName":"td","properties":{},"children":[{"type":"text","value":"Bandages"}]},{"type":"element","tagName":"td","properties":{},"children":[{"type":"text","value":"Brass knuckles (light)"}]}]},{"type":"element","tagName":"tr","properties":{},"children":[{"type":"element","tagName":"td","properties":{},"children":[{"type":"text","value":"72"}]},{"type":"element","tagName":"td","properties":{},"children":[{"type":"text","value":"Professional Duelist"}]},{"type":"element","tagName":"td","properties":{},"children":[{"type":"text","value":"Pocketwatch"}]},{"type":"element","tagName":"td","properties":{},"children":[{"type":"text","value":"Small bell"}]},{"type":"element","tagName":"td","properties":{},"children":[{"type":"text","value":"Rapier (medium)"}]}]},{"type":"element","tagName":"tr","properties":{},"children":[{"type":"element","tagName":"td","properties":{},"children":[{"type":"text","value":"73"}]},{"type":"element","tagName":"td","properties":{},"children":[{"type":"text","value":"Radical Pamphleteer"}]},{"type":"element","tagName":"td","properties":{},"children":[{"type":"text","value":"Bundle of paper"}]},{"type":"element","tagName":"td","properties":{},"children":[{"type":"text","value":"Nails"}]},{"type":"element","tagName":"td","properties":{},"children":[{"type":"text","value":"Pistol"}]}]},{"type":"element","tagName":"tr","properties":{},"children":[{"type":"element","tagName":"td","properties":{},"children":[{"type":"text","value":"74"}]},{"type":"element","tagName":"td","properties":{},"children":[{"type":"text","value":"Rag Collector"}]},{"type":"element","tagName":"td","properties":{},"children":[{"type":"text","value":"Bag of rags"}]},{"type":"element","tagName":"td","properties":{},"children":[{"type":"text","value":"Twine (300ft)"}]},{"type":"element","tagName":"td","properties":{},"children":[{"type":"text","value":"Wooden club (light)"}]}]},{"type":"element","tagName":"tr","properties":{},"children":[{"type":"element","tagName":"td","properties":{},"children":[{"type":"text","value":"75"}]},{"type":"element","tagName":"td","properties":{},"children":[{"type":"text","value":"Regretful Kidnapper"}]},{"type":"element","tagName":"td","properties":{},"children":[{"type":"text","value":"Angry child"}]},{"type":"element","tagName":"td","properties":{},"children":[{"type":"text","value":"Sack"}]},{"type":"element","tagName":"td","properties":{},"children":[{"type":"text","value":"Sword (medium)"}]}]},{"type":"element","tagName":"tr","properties":{},"children":[{"type":"element","tagName":"td","properties":{},"children":[{"type":"text","value":"76"}]},{"type":"element","tagName":"td","properties":{},"children":[{"type":"text","value":"Roach Gang Breeder"}]},{"type":"element","tagName":"td","properties":{},"children":[{"type":"text","value":"Wooden spikes"}]},{"type":"element","tagName":"td","properties":{},"children":[{"type":"text","value":"Trained cockroach"}]},{"type":"element","tagName":"td","properties":{},"children":[{"type":"text","value":"Whip (light)"}]}]},{"type":"element","tagName":"tr","properties":{},"children":[{"type":"element","tagName":"td","properties":{},"children":[{"type":"text","value":"77"}]},{"type":"element","tagName":"td","properties":{},"children":[{"type":"text","value":"Roaming Knife Sharpener"}]},{"type":"element","tagName":"td","properties":{},"children":[{"type":"text","value":"Whetstone"}]},{"type":"element","tagName":"td","properties":{},"children":[{"type":"text","value":"Metal file"}]},{"type":"element","tagName":"td","properties":{},"children":[{"type":"text","value":"Dagger (light)"}]}]},{"type":"element","tagName":"tr","properties":{},"children":[{"type":"element","tagName":"td","properties":{},"children":[{"type":"text","value":"78"}]},{"type":"element","tagName":"td","properties":{},"children":[{"type":"text","value":"Rooftop Hawker"}]},{"type":"element","tagName":"td","properties":{},"children":[{"type":"text","value":"Basket"}]},{"type":"element","tagName":"td","properties":{},"children":[{"type":"text","value":"Rope (50ft)"}]},{"type":"element","tagName":"td","properties":{},"children":[]}]},{"type":"element","tagName":"tr","properties":{},"children":[{"type":"element","tagName":"td","properties":{},"children":[{"type":"text","value":"79"}]},{"type":"element","tagName":"td","properties":{},"children":[{"type":"text","value":"Safe-breaker"}]},{"type":"element","tagName":"td","properties":{},"children":[{"type":"text","value":"Hand drill"}]},{"type":"element","tagName":"td","properties":{},"children":[{"type":"text","value":"Hammer"}]},{"type":"element","tagName":"td","properties":{},"children":[{"type":"text","value":"Pistol"}]}]},{"type":"element","tagName":"tr","properties":{},"children":[{"type":"element","tagName":"td","properties":{},"children":[{"type":"text","value":"80"}]},{"type":"element","tagName":"td","properties":{},"children":[{"type":"text","value":"Secret Robot"}]},{"type":"element","tagName":"td","properties":{},"children":[{"type":"text","value":"Flask of engine oil"}]},{"type":"element","tagName":"td","properties":{},"children":[{"type":"text","value":"Special: Detachable face"}]},{"type":"element","tagName":"td","properties":{},"children":[{"type":"text","value":"Pistol"}]}]},{"type":"element","tagName":"tr","properties":{},"children":[{"type":"element","tagName":"td","properties":{},"children":[{"type":"text","value":"81"}]},{"type":"element","tagName":"td","properties":{},"children":[{"type":"text","value":"Sewer Surveyor"}]},{"type":"element","tagName":"td","properties":{},"children":[{"type":"text","value":"Lantern"}]},{"type":"element","tagName":"td","properties":{},"children":[{"type":"text","value":"Rope (50ft)"}]},{"type":"element","tagName":"td","properties":{},"children":[{"type":"text","value":"Wooden club (light)"}]}]},{"type":"element","tagName":"tr","properties":{},"children":[{"type":"element","tagName":"td","properties":{},"children":[{"type":"text","value":"82"}]},{"type":"element","tagName":"td","properties":{},"children":[{"type":"text","value":"Shingle Layer"}]},{"type":"element","tagName":"td","properties":{},"children":[{"type":"text","value":"Crowbar"}]},{"type":"element","tagName":"td","properties":{},"children":[{"type":"text","value":"Climbing boots"}]},{"type":"element","tagName":"td","properties":{},"children":[]}]},{"type":"element","tagName":"tr","properties":{},"children":[{"type":"element","tagName":"td","properties":{},"children":[{"type":"text","value":"83"}]},{"type":"element","tagName":"td","properties":{},"children":[{"type":"text","value":"Signboard Spinner"}]},{"type":"element","tagName":"td","properties":{},"children":[{"type":"text","value":"Signboard (as Shield)"}]},{"type":"element","tagName":"td","properties":{},"children":[{"type":"text","value":"Horn"}]},{"type":"element","tagName":"td","properties":{},"children":[{"type":"text","value":"Wooden club (light)"}]}]},{"type":"element","tagName":"tr","properties":{},"children":[{"type":"element","tagName":"td","properties":{},"children":[{"type":"text","value":"84"}]},{"type":"element","tagName":"td","properties":{},"children":[{"type":"text","value":"Siltriver Bargeman"}]},{"type":"element","tagName":"td","properties":{},"children":[{"type":"text","value":"Bucket"}]},{"type":"element","tagName":"td","properties":{},"children":[{"type":"text","value":"Fishing rod & tackle"}]},{"type":"element","tagName":"td","properties":{},"children":[{"type":"text","value":"Oar (light)"}]}]},{"type":"element","tagName":"tr","properties":{},"children":[{"type":"element","tagName":"td","properties":{},"children":[{"type":"text","value":"85"}]},{"type":"element","tagName":"td","properties":{},"children":[{"type":"text","value":"Slaughterhouse Knifeman"}]},{"type":"element","tagName":"td","properties":{},"children":[{"type":"text","value":"Bag of salt"}]},{"type":"element","tagName":"td","properties":{},"children":[{"type":"text","value":"Saw"}]},{"type":"element","tagName":"td","properties":{},"children":[{"type":"text","value":"Cleaver (light)"}]}]},{"type":"element","tagName":"tr","properties":{},"children":[{"type":"element","tagName":"td","properties":{},"children":[{"type":"text","value":"86"}]},{"type":"element","tagName":"td","properties":{},"children":[{"type":"text","value":"Sod Burner"}]},{"type":"element","tagName":"td","properties":{},"children":[{"type":"text","value":"Shovel"}]},{"type":"element","tagName":"td","properties":{},"children":[{"type":"text","value":"Bag of charcoal"}]},{"type":"element","tagName":"td","properties":{},"children":[{"type":"text","value":"Pitchfork (medium)"}]}]},{"type":"element","tagName":"tr","properties":{},"children":[{"type":"element","tagName":"td","properties":{},"children":[{"type":"text","value":"87"}]},{"type":"element","tagName":"td","properties":{},"children":[{"type":"text","value":"Street Performer"}]},{"type":"element","tagName":"td","properties":{},"children":[{"type":"text","value":"Musical instrument"}]},{"type":"element","tagName":"td","properties":{},"children":[{"type":"text","value":"Face paint"}]},{"type":"element","tagName":"td","properties":{},"children":[{"type":"text","value":"Sword (medium)"}]}]},{"type":"element","tagName":"tr","properties":{},"children":[{"type":"element","tagName":"td","properties":{},"children":[{"type":"text","value":"88"}]},{"type":"element","tagName":"td","properties":{},"children":[{"type":"text","value":"Sunken-land Refugee"}]},{"type":"element","tagName":"td","properties":{},"children":[{"type":"text","value":"Waterproof trousers"}]},{"type":"element","tagName":"td","properties":{},"children":[{"type":"text","value":"Goat"}]},{"type":"element","tagName":"td","properties":{},"children":[{"type":"text","value":"Pitchfork (medium)"}]}]},{"type":"element","tagName":"tr","properties":{},"children":[{"type":"element","tagName":"td","properties":{},"children":[{"type":"text","value":"89"}]},{"type":"element","tagName":"td","properties":{},"children":[{"type":"text","value":"Sunken-land Wanderer"}]},{"type":"element","tagName":"td","properties":{},"children":[{"type":"text","value":"Mule"}]},{"type":"element","tagName":"td","properties":{},"children":[{"type":"text","value":"Random Device"}]},{"type":"element","tagName":"td","properties":{},"children":[]}]},{"type":"element","tagName":"tr","properties":{},"children":[{"type":"element","tagName":"td","properties":{},"children":[{"type":"text","value":"90"}]},{"type":"element","tagName":"td","properties":{},"children":[{"type":"text","value":"Swamp Fisherman"}]},{"type":"element","tagName":"td","properties":{},"children":[{"type":"text","value":"Pair of stilts"}]},{"type":"element","tagName":"td","properties":{},"children":[{"type":"text","value":"Smoked eel"}]},{"type":"element","tagName":"td","properties":{},"children":[{"type":"text","value":"Spear (medium)"}]}]},{"type":"element","tagName":"tr","properties":{},"children":[{"type":"element","tagName":"td","properties":{},"children":[{"type":"text","value":"91"}]},{"type":"element","tagName":"td","properties":{},"children":[{"type":"text","value":"Sweeper's Assistant"}]},{"type":"element","tagName":"td","properties":{},"children":[{"type":"text","value":"Broom"}]},{"type":"element","tagName":"td","properties":{},"children":[{"type":"text","value":"Bellows"}]},{"type":"element","tagName":"td","properties":{},"children":[{"type":"text","value":"Staff (light)"}]}]},{"type":"element","tagName":"tr","properties":{},"children":[{"type":"element","tagName":"td","properties":{},"children":[{"type":"text","value":"92"}]},{"type":"element","tagName":"td","properties":{},"children":[{"type":"text","value":"Talentless Wizard"}]},{"type":"element","tagName":"td","properties":{},"children":[{"type":"text","value":"Pointy hat"}]},{"type":"element","tagName":"td","properties":{},"children":[{"type":"text","value":"Random Device"}]},{"type":"element","tagName":"td","properties":{},"children":[{"type":"text","value":"Staff (light)"}]}]},{"type":"element","tagName":"tr","properties":{},"children":[{"type":"element","tagName":"td","properties":{},"children":[{"type":"text","value":"93"}]},{"type":"element","tagName":"td","properties":{},"children":[{"type":"text","value":"Test Subject"}]},{"type":"element","tagName":"td","properties":{},"children":[{"type":"text","value":"Flask of glue"}]},{"type":"element","tagName":"td","properties":{},"children":[{"type":"text","value":"Special: Extra... (1-3 arm; 4 leg; 5 eye; 6 head)"}]},{"type":"element","tagName":"td","properties":{},"children":[{"type":"text","value":"Club (light)"}]}]},{"type":"element","tagName":"tr","properties":{},"children":[{"type":"element","tagName":"td","properties":{},"children":[{"type":"text","value":"94"}]},{"type":"element","tagName":"td","properties":{},"children":[{"type":"text","value":"Tower Urchin"}]},{"type":"element","tagName":"td","properties":{},"children":[{"type":"text","value":"Rope (50ft)"}]},{"type":"element","tagName":"td","properties":{},"children":[{"type":"text","value":"Raven"}]},{"type":"element","tagName":"td","properties":{},"children":[{"type":"text","value":"Climbing pick (light)"}]}]},{"type":"element","tagName":"tr","properties":{},"children":[{"type":"element","tagName":"td","properties":{},"children":[{"type":"text","value":"95"}]},{"type":"element","tagName":"td","properties":{},"children":[{"type":"text","value":"Travelling Seller"}]},{"type":"element","tagName":"td","properties":{},"children":[{"type":"text","value":"Eel pie"}]},{"type":"element","tagName":"td","properties":{},"children":[{"type":"text","value":"Hand cart"}]},{"type":"element","tagName":"td","properties":{},"children":[{"type":"text","value":"Staff (light)"}]}]},{"type":"element","tagName":"tr","properties":{},"children":[{"type":"element","tagName":"td","properties":{},"children":[{"type":"text","value":"96"}]},{"type":"element","tagName":"td","properties":{},"children":[{"type":"text","value":"Undying City Diplomat"}]},{"type":"element","tagName":"td","properties":{},"children":[{"type":"text","value":"Expired passport"}]},{"type":"element","tagName":"td","properties":{},"children":[{"type":"text","value":"\"Special: If you die, 2-in-6 chance to return to life the next morning\""}]},{"type":"element","tagName":"td","properties":{},"children":[{"type":"text","value":"Pistol"}]}]},{"type":"element","tagName":"tr","properties":{},"children":[{"type":"element","tagName":"td","properties":{},"children":[{"type":"text","value":"97"}]},{"type":"element","tagName":"td","properties":{},"children":[{"type":"text","value":"Unlicensed Tax collector"}]},{"type":"element","tagName":"td","properties":{},"children":[{"type":"text","value":"Forged royal seal"}]},{"type":"element","tagName":"td","properties":{},"children":[{"type":"text","value":"Pen & ink"}]},{"type":"element","tagName":"td","properties":{},"children":[{"type":"text","value":"Club (light)"}]}]},{"type":"element","tagName":"tr","properties":{},"children":[{"type":"element","tagName":"td","properties":{},"children":[{"type":"text","value":"98"}]},{"type":"element","tagName":"td","properties":{},"children":[{"type":"text","value":"Vermin Hunter"}]},{"type":"element","tagName":"td","properties":{},"children":[{"type":"text","value":"Bear trap"}]},{"type":"element","tagName":"td","properties":{},"children":[{"type":"text","value":"Small vicious dog"}]},{"type":"element","tagName":"td","properties":{},"children":[{"type":"text","value":"Flail (medium)"}]}]},{"type":"element","tagName":"tr","properties":{},"children":[{"type":"element","tagName":"td","properties":{},"children":[{"type":"text","value":"99"}]},{"type":"element","tagName":"td","properties":{},"children":[{"type":"text","value":"Veteran of the Reach"}]},{"type":"element","tagName":"td","properties":{},"children":[{"type":"text","value":"Tattered soldier's uniform"}]},{"type":"element","tagName":"td","properties":{},"children":[{"type":"text","value":"Crutch"}]},{"type":"element","tagName":"td","properties":{},"children":[{"type":"text","value":"Rifle"}]}]},{"type":"element","tagName":"tr","properties":{},"children":[{"type":"element","tagName":"td","properties":{},"children":[{"type":"text","value":"100"}]},{"type":"element","tagName":"td","properties":{},"children":[{"type":"text","value":"Window Knocker"}]},{"type":"element","tagName":"td","properties":{},"children":[{"type":"text","value":"Lantern"}]},{"type":"element","tagName":"td","properties":{},"children":[{"type":"text","value":"Rope (50ft)"}]},{"type":"element","tagName":"td","properties":{},"children":[{"type":"text","value":"Long pole (light)"}]}]}]}]}],"data":{"quirksMode":false}},"excerpt":"d100 Failed career Item 1 Item 2 Weapon 1 Afterlife Messenger Rope (50ft) Smelling salts Scalpel (light) 2 Alehouse Keeper Small barrel of","frontmatter":{"date":"October 31, 2018","title":"Failed career tables","image":null}}},"pageContext":{"slug":"/__background-tables/"}}